README.md
setup.py
Data4FAE/Data4FAE.py
Data4FAE/__init__.py
Data4FAE.egg-info/PKG-INFO
Data4FAE.egg-info/SOURCES.txt
Data4FAE.egg-info/dependency_links.txt
Data4FAE.egg-info/requires.txt
Data4FAE.egg-info/top_level.txt