Metadata-Version: 2.1
Name: Data4FAE
Version: 0.0.1
Summary: Python package for Satellogic interview
Home-page: UNKNOWN
Author: Gabriel Rosso
Author-email: <rosso.gabriel1@gmail.com>
License: UNKNOWN
Keywords: python,first package
Platform: UNKNOWN
Classifier: Programming Language :: Python :: 3
Classifier: Operating System :: OS Independent
